{"clientVersionFromXml": "0, 7, 12, 1219756", "gameMode": 11, "clientVersionFromExe": "0, 7, 12, 1219756", "scenarioUiCategoryId": 0, "mapDisplayName": "08_NE_passage", "mapId": 5, "matchGroup": "pvp", "weatherParams": {"0": ["PCOW005_Evening"], "1": ["PCOW003_Cloudy"], "2": ["PCOW003_Cloudy", "PCOW002_Storm"]}, "duration": 1200, "gameLogic": "Domination", "name": "12x12", "scenario": "Domination_2_BASES", "playerID": 0, "vehicles": [{"shipId": 4183734096, "relation": 1, "id": 539025284, "name": "jfz20020523"}, {"shipId": 4290655952, "relation": 2, "id": 538987528, "name": "sukifung"}, {"shipId": 4183734224, "relation": 1, "id": 538977930, "name": "Cleaveland"}, {"shipId": 4285511376, "relation": 1, "id": 673321616, "name": "CAT_271"}, {"shipId": 4292818896, "relation": 2, "id": 673310869, "name": "kuro_karasu"}, {"shipId": 4288657104, "relation": 1, "id": 673265686, "name": "_GYhz_"}, {"shipId": 4287575760, "relation": 2, "id": 673264279, "name": "HIMEKA"}, {"shipId": 4268635856, "relation": 1, "id": 539036164, "name": "nikingo"}, {"shipId": 4183766992, "relation": 1, "id": 673140382, "name": "jiafem"}, {"shipId": 4183766864, "relation": 2, "id": 673306534, "name": "Final_Exam"}, {"shipId": 4288657104, "relation": 2, "id": 539092916, "name": "nightary7"}, {"shipId": 4290655952, "relation": 2, "id": 673167926, "name": "hinatera"}, {"shipId": 3555669712, "relation": 0, "id": 673335223, "name": "tonango"}, {"shipId": 4285511376, "relation": 2, "id": 673160509, "name": "GMashiro"}, {"shipId": 4183701296, "relation": 2, "id": 539201477, "name": "Morlous_Rika"}, {"shipId": 4078876656, "relation": 2, "id": 538943687, "name": "Alinya"}, {"shipId": 3765384656, "relation": 1, "id": 673216713, "name": "nokoro"}, {"shipId": 4288624336, "relation": 2, "id": 538938955, "name": "JeamBeam_Black"}, {"shipId": 4183766864, "relation": 1, "id": 673200079, "name": "ArnoVictorDorian_2018"}, {"shipId": 3764303216, "relation": 2, "id": 539031126, "name": "misato_"}, {"shipId": 4183766992, "relation": 1, "id": 538822489, "name": "793090230"}, {"shipId": 4280170480, "relation": 1, "id": 673289716, "name": "sena_kotori"}, {"shipId": 4184815568, "relation": 2, "id": 673311735, "name": "1753836538"}, {"shipId": 4183701200, "relation": 1, "id": 673280217, "name": "Tyson_Locke"}], "playersPerTeam": 12, "dateTime": "05.01.2019 23:42:25", "mapName": "spaces/08_NE_passage", "playerName": "tonango", "scenarioConfigId": 35, "teamsCount": 2, "logic": "Domination", "playerVehicle": "PJSB705-Kongou"}