{"clientVersionFromXml": "0, 7, 12, 1219756", "gameMode": 7, "clientVersionFromExe": "0, 7, 12, 1219756", "scenarioUiCategoryId": 0, "mapDisplayName": "38_Canada", "mapId": 23, "matchGroup": "pvp", "weatherParams": {"0": ["PCOW003_Cloudy"], "1": ["PCOW009_Snowstorm_Logic", "PCOW003_Cloudy"]}, "duration": 1200, "gameLogic": "Domination", "name": "12x12", "scenario": "Domination", "playerID": 0, "vehicles": [{"shipId": 4273911792, "relation": 1, "id": 536883329, "name": "Terry_ham"}, {"shipId": 3761157584, "relation": 1, "id": 671132036, "name": "SycoraX81"}, {"shipId": 3762239184, "relation": 0, "id": 536900229, "name": "tonango"}, {"shipId": 4179539760, "relation": 2, "id": 536897675, "name": "Lampard_"}, {"shipId": 4065212112, "relation": 1, "id": 671132047, "name": "ko_parpun20"}, {"shipId": 3751753552, "relation": 2, "id": 671151379, "name": "outsiderwing"}, {"shipId": 3761157584, "relation": 2, "id": 536998294, "name": "Strelizia_DarlingZeroTwo"}, {"shipId": 4282267344, "relation": 2, "id": 671098395, "name": "See_mann"}, {"shipId": 3551410160, "relation": 2, "id": 671213475, "name": "rkffosk"}, {"shipId": 3761190896, "relation": 1, "id": 671093933, "name": "fukuryu_"}, {"shipId": 3760109008, "relation": 1, "id": 671105583, "name": "Deep_Dark_Fantasy_Baby"}, {"shipId": 4276041424, "relation": 1, "id": 671107903, "name": "SIYEXIAOXI"}, {"shipId": 4179572688, "relation": 2, "id": 537053507, "name": "liuiuuuuuu"}, {"shipId": 4179572528, "relation": 2, "id": 671153732, "name": "rykafire"}, {"shipId": 3762239312, "relation": 2, "id": 671139275, "name": "N_E_G_E_V"}, {"shipId": 4277090288, "relation": 1, "id": 537046352, "name": "Itsukas"}, {"shipId": 3551410160, "relation": 2, "id": 671165524, "name": "crazydee"}, {"shipId": 4179507152, "relation": 1, "id": 537000666, "name": "Hakurei_reimuPrPr"}, {"shipId": 4179539792, "relation": 1, "id": 671115231, "name": "Kaintoe"}, {"shipId": 4273911792, "relation": 2, "id": 671252194, "name": "ihabd"}, {"shipId": 4180555728, "relation": 1, "id": 536878564, "name": "Fayexu"}, {"shipId": 4276041424, "relation": 2, "id": 671266792, "name": "FLorensius_Christian_45"}, {"shipId": 4259231440, "relation": 2, "id": 537046389, "name": "sumi16"}, {"shipId": 4179572560, "relation": 1, "id": 537041657, "name": "RevWu"}], "playersPerTeam": 12, "dateTime": "18.01.2019 15:25:01", "mapName": "spaces/38_Canada", "playerName": "tonango", "scenarioConfigId": 182, "teamsCount": 2, "logic": "Domination", "playerVehicle": "PJSB508-Kii"}